client/__init__.py
client/add_contact.py
client/client_ui.py
client/database.py
client/del_contact.py
client/main_window.py
client/start_dialog.py
client/transport.py
common/__init__.py
common/decorators.py
common/descriptors.py
common/errors.py
common/metaclasses.py
common/utils.py
common/variables.py
logs/__init__.py
logs/config_client_log.py
unit_tests/__init__.py
nix86_mess_client-0.1.0.dist-info/METADATA
nix86_mess_client-0.1.0.dist-info/WHEEL
nix86_mess_client-0.1.0.dist-info/top_level.txt
nix86_mess_client-0.1.0.dist-info/RECORD
