Metadata-Version: 2.1
Name: nix86-mess-client
Version: 0.1.0
Summary: nix86_mess_client
Home-page: UNKNOWN
Author: NIx86
Author-email: nikrogoz@yandex.ru
License: UNKNOWN
Platform: UNKNOWN
Requires-Dist: PyQt5
Requires-Dist: sqlalchemy
Requires-Dist: pycryptodome
Requires-Dist: pycryptodomex
